dotflow/__init__.py
dotflow/abc/__init__.py
dotflow/abc/file.py
dotflow/abc/flow.py
dotflow/abc/http.py
dotflow/abc/log.py
dotflow/abc/notify.py
dotflow/abc/storage.py
dotflow/abc/tcp.py
dotflow/cli/__init__.py
dotflow/cli/command.py
dotflow/cli/commands/__init__.py
dotflow/cli/commands/init.py
dotflow/cli/commands/log.py
dotflow/cli/commands/start.py
dotflow/cli/setup.py
dotflow/cli/validators/__init__.py
dotflow/cli/validators/start.py
dotflow/core/__init__.py
dotflow/core/action.py
dotflow/core/config.py
dotflow/core/context.py
dotflow/core/decorators/__init__.py
dotflow/core/decorators/time.py
dotflow/core/dotflow.py
dotflow/core/exception.py
dotflow/core/execution.py
dotflow/core/module.py
dotflow/core/serializers/__init__.py
dotflow/core/serializers/task.py
dotflow/core/serializers/transport.py
dotflow/core/serializers/workflow.py
dotflow/core/task.py
dotflow/core/types/__init__.py
dotflow/core/types/execution.py
dotflow/core/types/status.py
dotflow/core/types/storage.py
dotflow/core/types/worflow.py
dotflow/core/workflow.py
dotflow/logging.py
dotflow/main.py
dotflow/providers/__init__.py
dotflow/providers/log_default.py
dotflow/providers/notify_default.py
dotflow/providers/notify_telegram.py
dotflow/providers/storage_default.py
dotflow/providers/storage_file.py
dotflow/settings.py
dotflow/storage.py
dotflow/types.py
dotflow/utils/__init__.py
dotflow/utils/basic_functions.py
dotflow/utils/error_handler.py
dotflow/utils/tools.py
dotflow-0.13.1.dist-info/LICENSE
dotflow-0.13.1.dist-info/METADATA
dotflow-0.13.1.dist-info/WHEEL
dotflow-0.13.1.dist-info/entry_points.txt
dotflow-0.13.1.dist-info/RECORD
