Metadata-Version: 2.3
Name: dotflow
Version: 0.13.1
Summary: 🎲 Dotflow turns an idea into flow!
License: MIT License
Author: Fernando Celmer
Author-email: email@fernandocelmer.com
Requires-Python: >=3.9
Classifier: Development Status :: 4 - Beta
Classifier: Operating System :: OS Independent
Classifier: Intended Audience :: Developers
Classifier: Natural Language :: English
Classifier: Programming Language :: Python :: 3.9
Classifier: Programming Language :: Python :: 3.10
Classifier: Programming Language :: Python :: 3.11
Classifier: Programming Language :: Python :: 3.12
Classifier: Programming Language :: Python :: 3.13
Provides-Extra: mongodb
Requires-Dist: dotflow-mongodb ; extra == "mongodb"
Requires-Dist: pydantic
Requires-Dist: requests
Requires-Dist: rich
Requires-Dist: typing-extensions
Project-URL: Documentation, https://github.com/dotflow-io/dotflow/blob/master/README.md
Project-URL: Homepage, https://github.com/dotflow-io/dotflow
Project-URL: Issues, https://github.com/dotflow-io/dotflow/issues
Project-URL: Repository, https://github.com/dotflow-io/dotflow
